pytest_cratedb_reporter/__init__.py
pytest_cratedb_reporter/plugin.py
pytest_cratedb_reporter-0.1.0.dist-info/LICENSE
pytest_cratedb_reporter-0.1.0.dist-info/METADATA
pytest_cratedb_reporter-0.1.0.dist-info/WHEEL
pytest_cratedb_reporter-0.1.0.dist-info/entry_points.txt
pytest_cratedb_reporter-0.1.0.dist-info/top_level.txt
pytest_cratedb_reporter-0.1.0.dist-info/RECORD
