Metadata-Version: 2.2
Name: pytest-cratedb-reporter
Version: 0.1.0
Summary: A pytest plugin for reporting test results to CrateDB
Author-email: Jonathan Kittell <jkittell@gmail.com>
License: MIT
Project-URL: Homepage, https://github.com/themodelarchitect/pytest-cratedb-reporter
Project-URL: Bug Tracker, https://github.com/themodelarchitect/pytest-cratedb-reporter/issues
Classifier: Framework :: Pytest
Classifier: Programming Language :: Python :: 3
Classifier: Programming Language :: Python :: 3.7
Classifier: Programming Language :: Python :: 3.8
Classifier: Programming Language :: Python :: 3.9
Classifier: Programming Language :: Python :: 3.10
Classifier: Programming Language :: Python :: 3.11
Classifier: License :: OSI Approved :: MIT License
Classifier: Operating System :: OS Independent
Requires-Python: >=3.7
License-File: LICENSE
Requires-Dist: pytest>=6.0.0
Requires-Dist: sqlalchemy-cratedb>=0.41.0
